classifier/__init__.py
classifier/exceptions.py
classifier/forms.py
classifier/formsets.py
classifier/models.py
django_classifier-0.2.2.1.dist-info/LICENSE.txt
django_classifier-0.2.2.1.dist-info/METADATA
django_classifier-0.2.2.1.dist-info/RECORD
django_classifier-0.2.2.1.dist-info/WHEEL
django_classifier-0.2.2.1.dist-info/top_level.txt
testapp/tests/__init__.py
testapp/tests/factories.py
testapp/tests/tests_forms.py
testapp/tests/tests_formset.py
testapp/tests/tests_model.py
