Metadata-Version: 2.1
Name: django-classifier
Version: 0.2.2.1
Summary: Flexible constructor to create dynamic list of heterogeneous properties for some kind of entity. This set of helpers useful to create properties like contacts or attributes for describe car/computer/etc.
Home-page: http://github.com/djangostars/djnago-classifier/
Author: Vadym Zakovinko
Author-email: vadym.zakovinko@djangostars.com
License: BSD
Platform: UNKNOWN
Classifier: Development Status :: 5 - Production/Stable
Classifier: Environment :: Web Environment
Classifier: Intended Audience :: Developers
Classifier: License :: OSI Approved :: BSD License
Classifier: Operating System :: OS Independent
Classifier: Programming Language :: Python
Classifier: Programming Language :: Python :: 2.7
Classifier: Programming Language :: Python :: 3
Classifier: Programming Language :: Python :: 3.3
Classifier: Programming Language :: Python :: 3.4
Classifier: Programming Language :: Python :: 3.5
Classifier: Programming Language :: Python :: 3.6
Classifier: Framework :: Django
Classifier: Framework :: Django :: 1.8
Classifier: Framework :: Django :: 1.9
Classifier: Framework :: Django :: 1.10
Classifier: Framework :: Django :: 1.11
Classifier: Framework :: Django :: 2.0
